ProxySuite/KD.py
ProxySuite/__init__.py
ProxySuite/checker.py
ProxySuite/flood.py
ProxySuite/main.py
ProxySuite/saver.py
ProxySuite/scraper.py
ProxySuite/spoof.py
ProxySuite/utils.py
ProxySuite-1.0.0.dist-info/METADATA
ProxySuite-1.0.0.dist-info/WHEEL
ProxySuite-1.0.0.dist-info/entry_points.txt
ProxySuite-1.0.0.dist-info/top_level.txt
ProxySuite-1.0.0.dist-info/RECORD
