Metadata-Version: 2.2
Name: ProxySuite
Version: 1.0.0
Summary: A powerful tool to scrape, check, and manage proxies.
Home-page: https://github.com/NotAdl22/ProxySuite
Author: chef_lilou
Author-email: georgang123@gmail.com
Classifier: Programming Language :: Python :: 3
Classifier: License :: OSI Approved :: MIT License
Classifier: Operating System :: OS Independent
Requires-Python: >=3.7
Requires-Dist: requests
Requires-Dist: colorama
Dynamic: author
Dynamic: author-email
Dynamic: classifier
Dynamic: description
Dynamic: description-content-type
Dynamic: home-page
Dynamic: requires-dist
Dynamic: requires-python
Dynamic: summary
